pentest_tls/__init__.py
pentest_tls/pentest_tls_cli.py
pentest_tls/port_scanner_cli.py
pentest_tls/assets/.DS_Store
pentest_tls/assets/common_1k_tcp_ports.txt
pentest_tls/assets/common_1k_udp_ports.txt
pentest_tls/ps/__init__.py
pentest_tls/ps/port_scanner.py
pentest_tls/utility/__init__.py
pentest_tls/utility/util.py
pentest_tls-0.1.12.dist-info/licenses/LICENSE
pentest_tls-0.1.12.dist-info/METADATA
pentest_tls-0.1.12.dist-info/WHEEL
pentest_tls-0.1.12.dist-info/entry_points.txt
pentest_tls-0.1.12.dist-info/top_level.txt
pentest_tls-0.1.12.dist-info/RECORD
