Metadata-Version: 2.4
Name: pentest_tls
Version: 0.1.12
Summary: A collection of Python pentest tools
Author-email: Owen Liu <abcd0112014@gmail.com>
License: MIT
License-File: LICENSE
Requires-Dist: pyfiglet>=1.0
Requires-Dist: argparse
Requires-Dist: scapy
Dynamic: license-file
